{
  "$schema": "https://mintlify.com/docs.json",
  "theme": "mint",
  "name": "Elimu Bora ERP Help Center",
  "colors": {
    "primary": "#840404",
    "light": "#bc7c7c",
    "dark": "#e2c6c6"
  },
  "favicon": "https://media.brand.dev/28107f06-65a0-45ce-9937-4bc6a00d197b.svg",
  "navbar": {
    "primary": {
      "type": "button",
      "label": "Get Started",
      "href": "https://elimuboraerp.com/contact/"
    },
    "links": [
      {
        "type": "button",
        "label": "Login",
        "href": "https://elimuboraerp.com/login"
      }
    ]
  },
  "navigation": {
    "tabs": [
      {
        "tab": "Documentation",
        "groups": [
          {
            "group": "Get Started",
            "pages": [
              "introduction",
              "quickstart",
              "roles-and-access"
            ]
          },
          {
            "group": "Academics",
            "pages": [
              "academics/curriculum-setup",
              "academics/assessments",
              "academics/report-cards",
              "academics/timetables"
            ]
          },
          {
            "group": "Attendance",
            "pages": [
              "attendance/taking-attendance",
              "attendance/follow-ups"
            ]
          },
          {
            "group": "Finance",
            "pages": [
              "finance/fee-management",
              "finance/payments",
              "finance/mpesa",
              "finance/student-wallet"
            ]
          },
          {
            "group": "Inventory",
            "pages": [
              "inventory/products-and-stock",
              "inventory/procurement",
              "inventory/requisitions"
            ]
          },
          {
            "group": "School Management",
            "pages": [
              "school/events",
              "school/notifications",
              "school/reports",
              "school/bulk-imports",
              "school/settings"
            ]
          }
        ]
      }
    ]
  },
  "appearance": {
    "default": "system"
  },
  "background": {
    "decoration": "grid"
  },
  "logo": {
    "light": "/images/elimubora-logo-primary.png",
    "dark": "/images/elimubora-logo-white.png"
  },
  "fonts": {
    "family": "Inter"
  },
  "footer": {
    "socials": {
      "x": "https://x.com/elimuboraerp",
      "linkedin": "https://www.linkedin.com/company/elimu-bora-solutions-co",
      "website": "https://elimuboraerp.com/",
      "instagram": "https://www.instagram.com/elimuboraerp",
      "facebook": "https://www.facebook.com/elimuborasolutions"
    }
  },
  "styling": {
    "eyebrows": "breadcrumbs",
    "latex": true
  },
  "icons": {
    "library": "lucide"
  }
}
